pc-actions-handler
setup.py
pc_actions_handler/__init__.py
pc_actions_handler/middleware.py
pc_actions_handler/server.py
pc_actions_handler.egg-info/PKG-INFO
pc_actions_handler.egg-info/SOURCES.txt
pc_actions_handler.egg-info/dependency_links.txt
pc_actions_handler.egg-info/not-zip-safe
pc_actions_handler.egg-info/requires.txt
pc_actions_handler.egg-info/top_level.txt