Metadata-Version: 2.1
Name: pc-actions-handler
Version: 0.1.0
Summary: A simple http server to handle desktop actions
Home-page: https://github.com/filipealvesdef/pc_actions_handler
Author: Filipe Alves
Author-email: filipe.alvesdefernando@gmail.com
License: UNKNOWN
Platform: UNKNOWN
